kdc/__init__.py
kdc/config.py
kdc/kube_dashboard.py
kdc/main.py
kdc/parsers.py
kdc_kubeconnector-1.7.7.dist-info/METADATA
kdc_kubeconnector-1.7.7.dist-info/WHEEL
kdc_kubeconnector-1.7.7.dist-info/entry_points.txt
kdc_kubeconnector-1.7.7.dist-info/top_level.txt
kdc_kubeconnector-1.7.7.dist-info/RECORD
