Metadata-Version: 2.1
Name: kdc-kubeconnector
Version: 1.7.7
Summary: Tool to work with kubernetes dashboard, if there is no kubectl access
Author: Oleksii Ostapov
Project-URL: Homepage, https://infopulse.com
Project-URL: Documentation, https://github.com/infopulse/kdc
Project-URL: Code, https://github.com/infopulse/kdc
Classifier: Topic :: Software Development :: Testing
Classifier: Development Status :: 3 - Alpha
Classifier: Environment :: Console
Classifier: License :: OSI Approved :: MIT License
Classifier: Operating System :: OS Independent
Classifier: Programming Language :: Python :: 3
Requires-Python: >=3.11
Requires-Dist: argparse >=1.4.0
Requires-Dist: requests >=2.31.0
Requires-Dist: prettytable >=3.10.0
Requires-Dist: toml >=0.10.2
Requires-Dist: pyperclip >=1.8.2
